[{"id":292422432828,"articles":[{"name":"Имя для новой статьи - Как же я прекрасен","article":[{"name":"Блок 1: 1000 и 1 причина почему я прекрасен","main":{"blocks":[{"key":"e2d8b","text":"1 2 3 4 5 6 7 8 9 10 11 12 13 14 15 16 17 18 19 20 21 22 23 24 25 26 27 28 29 30 31 32 33 34 35 36 37 38 39 40 41 42 43 44 45 46 47 48 49 50","type":"unstyled","depth":0,"inlineStyleRanges":[],"entityRanges":[],"data":{}}],"entityMap":{}},"sidebar":{"blocks":[{"key":"5apmi","text":"1 2 3 4 5 6 7 8 9 10 11 12 13 14 15 16 17 18 19 20 21 22 23 24 25 26 27 28 29 30 31 32 33 34 35 36 37 38 39 40 41 42 43 44 45 46 47 48 49 50 ","type":"unstyled","depth":0,"inlineStyleRanges":[{"offset":0,"length":140,"style":"color-rgb(255,255,255)"},{"offset":0,"length":140,"style":"bgcolor-rgb(25,25,25)"},{"offset":0,"length":140,"style":"fontsize-medium"},{"offset":0,"length":140,"style":"fontfamily-Segoe UI\", Tahoma, Geneva, Verdana, sans-serif"}],"entityRanges":[],"data":{}}],"entityMap":{}}},{"name":"Блок 1: 1000 и 1 причина почему я прекрасен","main":{"blocks":[{"key":"e2d8b","text":"1 2 3 4 5 6 7 8 9 10 11 12 13 14 15 16 17 18 19 20 21 22 23 24 25 26 27 28 29 30 31 32 33 34 35 36 37 38 39 40 41 42 43 44 45 46 47 48 49 50","type":"unstyled","depth":0,"inlineStyleRanges":[],"entityRanges":[],"data":{}}],"entityMap":{}},"sidebar":{"blocks":[{"key":"5apmi","text":"1 2 3 4 5 6 7 8 9 10 11 12 13 14 15 16 17 18 19 20 21 22 23 24 25 26 27 28 29 30 31 32 33 34 35 36 37 38 39 40 41 42 43 44 45 46 47 48 49 50 ","type":"unstyled","depth":0,"inlineStyleRanges":[{"offset":0,"length":140,"style":"color-rgb(255,255,255)"},{"offset":0,"length":140,"style":"bgcolor-rgb(25,25,25)"},{"offset":0,"length":140,"style":"fontsize-medium"},{"offset":0,"length":140,"style":"fontfamily-Segoe UI\", Tahoma, Geneva, Verdana, sans-serif"}],"entityRanges":[],"data":{}}],"entityMap":{}}},{"name":"12345678910","main":{"blocks":[{"key":"815av","text":"123","type":"unstyled","depth":0,"inlineStyleRanges":[],"entityRanges":[],"data":{}}],"entityMap":{}},"sidebar":{"blocks":[{"key":"c217a","text":"1234","type":"unstyled","depth":0,"inlineStyleRanges":[],"entityRanges":[],"data":{}}],"entityMap":{}}}],"id":28260333989,"roles":["knight 292422432828","noble 292422432828","king 292422432828"],"secrets":[{"roles":["knight 292422432828","noble 292422432828","king 292422432828"],"name":"1241234","main":{"blocks":[{"key":"4k2sl","text":"123412341234","type":"unstyled","depth":0,"inlineStyleRanges":[],"entityRanges":[],"data":{}}],"entityMap":{}},"sidebar":{"blocks":[{"key":"ccpit","text":"123412341234","type":"unstyled","depth":0,"inlineStyleRanges":[],"entityRanges":[],"data":{}}],"entityMap":{}}},{"roles":["noble 292422432828","king 292422432828"],"name":"123412341234","main":{"blocks":[{"key":"v4jc","text":"123412341234","type":"unstyled","depth":0,"inlineStyleRanges":[],"entityRanges":[],"data":{}}],"entityMap":{}},"sidebar":{"blocks":[{"key":"86i17","text":"123412314","type":"unstyled","depth":0,"inlineStyleRanges":[],"entityRanges":[],"data":{}}],"entityMap":{}}},{"roles":["king 292422432828"],"name":"123412341234","main":{"blocks":[{"key":"5av92","text":"1234123413414","type":"unstyled","depth":0,"inlineStyleRanges":[],"entityRanges":[],"data":{}}],"entityMap":{}},"sidebar":{"blocks":[{"key":"2qm8f","text":"1234123412432","type":"unstyled","depth":0,"inlineStyleRanges":[],"entityRanges":[],"data":{}}],"entityMap":{}}},{"roles":["knight 292422432828","noble 292422432828","king 292422432828"],"name":"12344325111111111111","main":{"blocks":[{"key":"aio3i","text":"1111111111111111111111","type":"unstyled","depth":0,"inlineStyleRanges":[],"entityRanges":[],"data":{}}],"entityMap":{}},"sidebar":{"blocks":[{"key":"auslv","text":"12121212121212","type":"unstyled","depth":0,"inlineStyleRanges":[],"entityRanges":[],"data":{}}],"entityMap":{}}}]},{"name":"Riga","article":[{"name":"History of Riga","main":{"blocks":[{"key":"3d1kv","text":"Founding","type":"header-two","depth":0,"inlineStyleRanges":[{"offset":0,"length":8,"style":"BOLD"}],"entityRanges":[],"data":{}},{"key":"1t63b","text":"The river Daugava has been a trade route since antiquity, part of the Vikings' Dvina–Dnieper navigation route to Byzantium.[25] A sheltered natural harbor 15 km (9.3 mi) upriver from the mouth of the Daugava—the site of today's Riga—has been recorded, as Duna Urbs, as early as the 2nd century.[25] It was settled by the Livs, a Finnic tribe.","type":"unstyled","depth":0,"inlineStyleRanges":[{"offset":0,"length":9,"style":"color-rgb(32,33,34)"},{"offset":10,"length":7,"style":"color-rgb(32,33,34)"},{"offset":18,"length":10,"style":"color-rgb(32,33,34)"},{"offset":29,"length":11,"style":"color-rgb(32,33,34)"},{"offset":41,"length":28,"style":"color-rgb(32,33,34)"},{"offset":70,"length":8,"style":"color-rgb(32,33,34)"},{"offset":79,"length":30,"style":"color-rgb(32,33,34)"},{"offset":110,"length":17,"style":"color-rgb(32,33,34)"},{"offset":128,"length":11,"style":"color-rgb(32,33,34)"},{"offset":140,"length":14,"style":"color-rgb(32,33,34)"},{"offset":155,"length":99,"style":"color-rgb(32,33,34)"},{"offset":255,"length":43,"style":"color-rgb(32,33,34)"},{"offset":299,"length":21,"style":"color-rgb(32,33,34)"},{"offset":321,"length":7,"style":"color-rgb(32,33,34)"},{"offset":329,"length":6,"style":"color-rgb(32,33,34)"},{"offset":336,"length":6,"style":"color-rgb(32,33,34)"},{"offset":0,"length":9,"style":"bgcolor-rgb(255,255,255)"},{"offset":10,"length":7,"style":"bgcolor-rgb(255,255,255)"},{"offset":18,"length":10,"style":"bgcolor-rgb(255,255,255)"},{"offset":29,"length":11,"style":"bgcolor-rgb(255,255,255)"},{"offset":41,"length":28,"style":"bgcolor-rgb(255,255,255)"},{"offset":70,"length":8,"style":"bgcolor-rgb(255,255,255)"},{"offset":79,"length":30,"style":"bgcolor-rgb(255,255,255)"},{"offset":110,"length":17,"style":"bgcolor-rgb(255,255,255)"},{"offset":128,"length":11,"style":"bgcolor-rgb(255,255,255)"},{"offset":140,"length":14,"style":"bgcolor-rgb(255,255,255)"},{"offset":155,"length":99,"style":"bgcolor-rgb(255,255,255)"},{"offset":255,"length":43,"style":"bgcolor-rgb(255,255,255)"},{"offset":299,"length":21,"style":"bgcolor-rgb(255,255,255)"},{"offset":321,"length":7,"style":"bgcolor-rgb(255,255,255)"},{"offset":329,"length":6,"style":"bgcolor-rgb(255,255,255)"},{"offset":336,"length":6,"style":"bgcolor-rgb(255,255,255)"},{"offset":0,"length":9,"style":"fontsize-14"},{"offset":10,"length":7,"style":"fontsize-14"},{"offset":18,"length":10,"style":"fontsize-14"},{"offset":29,"length":11,"style":"fontsize-14"},{"offset":41,"length":28,"style":"fontsize-14"},{"offset":70,"length":8,"style":"fontsize-14"},{"offset":79,"length":30,"style":"fontsize-14"},{"offset":110,"length":17,"style":"fontsize-14"},{"offset":128,"length":11,"style":"fontsize-14"},{"offset":140,"length":14,"style":"fontsize-14"},{"offset":155,"length":99,"style":"fontsize-14"},{"offset":255,"length":43,"style":"fontsize-14"},{"offset":299,"length":21,"style":"fontsize-14"},{"offset":321,"length":7,"style":"fontsize-14"},{"offset":329,"length":6,"style":"fontsize-14"},{"offset":336,"length":6,"style":"fontsize-14"},{"offset":0,"length":9,"style":"fontfamily-sans-serif"},{"offset":10,"length":7,"style":"fontfamily-sans-serif"},{"offset":18,"length":10,"style":"fontfamily-sans-serif"},{"offset":29,"length":11,"style":"fontfamily-sans-serif"},{"offset":41,"length":28,"style":"fontfamily-sans-serif"},{"offset":70,"length":8,"style":"fontfamily-sans-serif"},{"offset":79,"length":30,"style":"fontfamily-sans-serif"},{"offset":110,"length":17,"style":"fontfamily-sans-serif"},{"offset":128,"length":11,"style":"fontfamily-sans-serif"},{"offset":140,"length":14,"style":"fontfamily-sans-serif"},{"offset":155,"length":99,"style":"fontfamily-sans-serif"},{"offset":255,"length":43,"style":"fontfamily-sans-serif"},{"offset":299,"length":21,"style":"fontfamily-sans-serif"},{"offset":321,"length":7,"style":"fontfamily-sans-serif"},{"offset":329,"length":6,"style":"fontfamily-sans-serif"},{"offset":336,"length":6,"style":"fontfamily-sans-serif"},{"offset":10,"length":7,"style":"color-rgb(51,102,204)"},{"offset":29,"length":11,"style":"color-rgb(51,102,204)"},{"offset":70,"length":8,"style":"color-rgb(51,102,204)"},{"offset":79,"length":30,"style":"color-rgb(51,102,204)"},{"offset":123,"length":4,"style":"color-rgb(51,102,204)"},{"offset":140,"length":14,"style":"color-rgb(51,102,204)"},{"offset":294,"length":4,"style":"color-rgb(51,102,204)"},{"offset":321,"length":4,"style":"color-rgb(51,102,204)"},{"offset":329,"length":6,"style":"color-rgb(51,102,204)"},{"offset":10,"length":7,"style":"bgcolor-initial"},{"offset":29,"length":11,"style":"bgcolor-initial"},{"offset":70,"length":8,"style":"bgcolor-initial"},{"offset":79,"length":30,"style":"bgcolor-initial"},{"offset":123,"length":4,"style":"bgcolor-initial"},{"offset":140,"length":14,"style":"bgcolor-initial"},{"offset":294,"length":4,"style":"bgcolor-initial"},{"offset":321,"length":4,"style":"bgcolor-initial"},{"offset":329,"length":6,"style":"bgcolor-initial"},{"offset":123,"length":4,"style":"SUPERSCRIPT"},{"offset":294,"length":4,"style":"SUPERSCRIPT"}],"entityRanges":[{"offset":10,"length":7,"key":0},{"offset":29,"length":11,"key":1},{"offset":70,"length":8,"key":2},{"offset":79,"length":30,"key":3},{"offset":123,"length":4,"key":4},{"offset":140,"length":14,"key":5},{"offset":294,"length":4,"key":6},{"offset":321,"length":4,"key":7},{"offset":329,"length":6,"key":8}],"data":{"text-align":"start"}},{"key":"3cd53","text":"","type":"atomic","depth":0,"inlineStyleRanges":[],"entityRanges":[],"data":{"text-align":"center"}},{"key":"dtd1i","text":" The building of the Brotherhood of Blackheads is one of the most iconic buildings of Old Riga (Vecrīga).","type":"atomic","depth":0,"inlineStyleRanges":[{"offset":1,"length":3,"style":"color-rgb(32,33,34)"},{"offset":5,"length":41,"style":"color-rgb(32,33,34)"},{"offset":47,"length":58,"style":"color-rgb(32,33,34)"},{"offset":1,"length":3,"style":"bgcolor-rgb(248,249,250)"},{"offset":5,"length":41,"style":"bgcolor-rgb(248,249,250)"},{"offset":47,"length":58,"style":"bgcolor-rgb(248,249,250)"},{"offset":1,"length":3,"style":"fontsize-14"},{"offset":5,"length":41,"style":"fontsize-14"},{"offset":47,"length":58,"style":"fontsize-14"},{"offset":1,"length":3,"style":"fontfamily-sans-serif"},{"offset":5,"length":41,"style":"fontfamily-sans-serif"},{"offset":47,"length":58,"style":"fontfamily-sans-serif"},{"offset":1,"length":3,"style":"fontsize-12.376"},{"offset":5,"length":41,"style":"fontsize-12.376"},{"offset":47,"length":58,"style":"fontsize-12.376"},{"offset":5,"length":41,"style":"color-rgb(51,102,204)"},{"offset":96,"length":7,"style":"color-rgb(51,102,204)"},{"offset":5,"length":41,"style":"bgcolor-initial"},{"offset":96,"length":7,"style":"bgcolor-initial"}],"entityRanges":[{"offset":0,"length":1,"key":9},{"offset":5,"length":41,"key":10},{"offset":96,"length":7,"key":11}],"data":{}},{"key":"1ve0b","text":"Riga began to develop as a centre of Viking trade during the early Middle Ages.[25] Riga's inhabitants occupied themselves mainly with fishing, animal husbandry, and trading, later developing crafts (in bone, wood, amber, and iron).[25]","type":"unstyled","depth":0,"inlineStyleRanges":[{"offset":0,"length":36,"style":"color-rgb(32,33,34)"},{"offset":37,"length":46,"style":"color-rgb(32,33,34)"},{"offset":84,"length":59,"style":"color-rgb(32,33,34)"},{"offset":144,"length":92,"style":"color-rgb(32,33,34)"},{"offset":0,"length":36,"style":"bgcolor-rgb(255,255,255)"},{"offset":37,"length":46,"style":"bgcolor-rgb(255,255,255)"},{"offset":84,"length":59,"style":"bgcolor-rgb(255,255,255)"},{"offset":144,"length":92,"style":"bgcolor-rgb(255,255,255)"},{"offset":0,"length":36,"style":"fontsize-14"},{"offset":37,"length":46,"style":"fontsize-14"},{"offset":84,"length":59,"style":"fontsize-14"},{"offset":144,"length":92,"style":"fontsize-14"},{"offset":0,"length":36,"style":"fontfamily-sans-serif"},{"offset":37,"length":46,"style":"fontfamily-sans-serif"},{"offset":84,"length":59,"style":"fontfamily-sans-serif"},{"offset":144,"length":92,"style":"fontfamily-sans-serif"},{"offset":37,"length":41,"style":"color-rgb(51,102,204)"},{"offset":79,"length":4,"style":"color-rgb(51,102,204)"},{"offset":144,"length":16,"style":"color-rgb(51,102,204)"},{"offset":232,"length":4,"style":"color-rgb(51,102,204)"},{"offset":37,"length":41,"style":"bgcolor-initial"},{"offset":79,"length":4,"style":"bgcolor-initial"},{"offset":144,"length":16,"style":"bgcolor-initial"},{"offset":232,"length":4,"style":"bgcolor-initial"},{"offset":79,"length":4,"style":"SUPERSCRIPT"},{"offset":232,"length":4,"style":"SUPERSCRIPT"}],"entityRanges":[{"offset":37,"length":41,"key":12},{"offset":79,"length":4,"key":13},{"offset":144,"length":16,"key":14},{"offset":232,"length":4,"key":15}],"data":{"text-align":"start"}},{"key":"32ecb","text":"The Livonian Chronicle of Henry testifies to Riga having long been a trading centre by the 12th century, referring to it as portus antiquus (ancient port), and describes dwellings and warehouses used to store mostly flax, and hides.[25] German traders began visiting Riga, establishing a nearby outpost in 1158.","type":"unstyled","depth":0,"inlineStyleRanges":[{"offset":0,"length":3,"style":"color-rgb(32,33,34)"},{"offset":4,"length":27,"style":"color-rgb(32,33,34)"},{"offset":32,"length":91,"style":"color-rgb(32,33,34)"},{"offset":124,"length":15,"style":"color-rgb(32,33,34)"},{"offset":140,"length":96,"style":"color-rgb(32,33,34)"},{"offset":237,"length":74,"style":"color-rgb(32,33,34)"},{"offset":0,"length":3,"style":"bgcolor-rgb(255,255,255)"},{"offset":4,"length":27,"style":"bgcolor-rgb(255,255,255)"},{"offset":32,"length":91,"style":"bgcolor-rgb(255,255,255)"},{"offset":124,"length":15,"style":"bgcolor-rgb(255,255,255)"},{"offset":140,"length":96,"style":"bgcolor-rgb(255,255,255)"},{"offset":237,"length":74,"style":"bgcolor-rgb(255,255,255)"},{"offset":0,"length":3,"style":"fontsize-14"},{"offset":4,"length":27,"style":"fontsize-14"},{"offset":32,"length":91,"style":"fontsize-14"},{"offset":124,"length":15,"style":"fontsize-14"},{"offset":140,"length":96,"style":"fontsize-14"},{"offset":237,"length":74,"style":"fontsize-14"},{"offset":0,"length":3,"style":"fontfamily-sans-serif"},{"offset":4,"length":27,"style":"fontfamily-sans-serif"},{"offset":32,"length":91,"style":"fontfamily-sans-serif"},{"offset":124,"length":15,"style":"fontfamily-sans-serif"},{"offset":140,"length":96,"style":"fontfamily-sans-serif"},{"offset":237,"length":74,"style":"fontfamily-sans-serif"},{"offset":4,"length":27,"style":"color-rgb(51,102,204)"},{"offset":232,"length":4,"style":"color-rgb(51,102,204)"},{"offset":4,"length":27,"style":"bgcolor-initial"},{"offset":232,"length":4,"style":"bgcolor-initial"},{"offset":232,"length":4,"style":"SUPERSCRIPT"}],"entityRanges":[{"offset":4,"length":27,"key":16},{"offset":232,"length":4,"key":17}],"data":{"text-align":"start"}},{"key":"5pcca","text":"Along with German traders the monk Meinhard of Segeberg[26] arrived to convert the Livonian pagans to Christianity. Catholic and Orthodox Christianity had already arrived in Latvia more than a century earlier, and many Latvians had been baptized.[25][26] Meinhard settled among the Livs, building a castle and church at Uexküll (now known as Ikšķile), upstream from Riga, and established his bishopric there.[26] The Livs, however, continued to practice paganism and Meinhard died in Uexküll in 1196, having failed in his mission.[27] In 1198, the Bishop Berthold arrived with a contingent of crusaders[27] and commenced a campaign of forced Christianization.[25][26] Berthold died soon afterwards and his forces were defeated.[27]","type":"unstyled","depth":0,"inlineStyleRanges":[{"offset":0,"length":34,"style":"color-rgb(32,33,34)"},{"offset":35,"length":24,"style":"color-rgb(32,33,34)"},{"offset":60,"length":55,"style":"color-rgb(32,33,34)"},{"offset":116,"length":8,"style":"color-rgb(32,33,34)"},{"offset":125,"length":3,"style":"color-rgb(32,33,34)"},{"offset":129,"length":21,"style":"color-rgb(32,33,34)"},{"offset":151,"length":103,"style":"color-rgb(32,33,34)"},{"offset":255,"length":86,"style":"color-rgb(32,33,34)"},{"offset":342,"length":70,"style":"color-rgb(32,33,34)"},{"offset":413,"length":40,"style":"color-rgb(32,33,34)"},{"offset":454,"length":8,"style":"color-rgb(32,33,34)"},{"offset":463,"length":71,"style":"color-rgb(32,33,34)"},{"offset":535,"length":12,"style":"color-rgb(32,33,34)"},{"offset":548,"length":15,"style":"color-rgb(32,33,34)"},{"offset":564,"length":28,"style":"color-rgb(32,33,34)"},{"offset":593,"length":13,"style":"color-rgb(32,33,34)"},{"offset":607,"length":34,"style":"color-rgb(32,33,34)"},{"offset":642,"length":25,"style":"color-rgb(32,33,34)"},{"offset":668,"length":63,"style":"color-rgb(32,33,34)"},{"offset":0,"length":34,"style":"bgcolor-rgb(255,255,255)"},{"offset":35,"length":24,"style":"bgcolor-rgb(255,255,255)"},{"offset":60,"length":55,"style":"bgcolor-rgb(255,255,255)"},{"offset":116,"length":8,"style":"bgcolor-rgb(255,255,255)"},{"offset":125,"length":3,"style":"bgcolor-rgb(255,255,255)"},{"offset":129,"length":21,"style":"bgcolor-rgb(255,255,255)"},{"offset":151,"length":103,"style":"bgcolor-rgb(255,255,255)"},{"offset":255,"length":86,"style":"bgcolor-rgb(255,255,255)"},{"offset":342,"length":70,"style":"bgcolor-rgb(255,255,255)"},{"offset":413,"length":40,"style":"bgcolor-rgb(255,255,255)"},{"offset":454,"length":8,"style":"bgcolor-rgb(255,255,255)"},{"offset":463,"length":71,"style":"bgcolor-rgb(255,255,255)"},{"offset":535,"length":12,"style":"bgcolor-rgb(255,255,255)"},{"offset":548,"length":15,"style":"bgcolor-rgb(255,255,255)"},{"offset":564,"length":28,"style":"bgcolor-rgb(255,255,255)"},{"offset":593,"length":13,"style":"bgcolor-rgb(255,255,255)"},{"offset":607,"length":34,"style":"bgcolor-rgb(255,255,255)"},{"offset":642,"length":25,"style":"bgcolor-rgb(255,255,255)"},{"offset":668,"length":63,"style":"bgcolor-rgb(255,255,255)"},{"offset":0,"length":34,"style":"fontsize-14"},{"offset":35,"length":24,"style":"fontsize-14"},{"offset":60,"length":55,"style":"fontsize-14"},{"offset":116,"length":8,"style":"fontsize-14"},{"offset":125,"length":3,"style":"fontsize-14"},{"offset":129,"length":21,"style":"fontsize-14"},{"offset":151,"length":103,"style":"fontsize-14"},{"offset":255,"length":86,"style":"fontsize-14"},{"offset":342,"length":70,"style":"fontsize-14"},{"offset":413,"length":40,"style":"fontsize-14"},{"offset":454,"length":8,"style":"fontsize-14"},{"offset":463,"length":71,"style":"fontsize-14"},{"offset":535,"length":12,"style":"fontsize-14"},{"offset":548,"length":15,"style":"fontsize-14"},{"offset":564,"length":28,"style":"fontsize-14"},{"offset":593,"length":13,"style":"fontsize-14"},{"offset":607,"length":34,"style":"fontsize-14"},{"offset":642,"length":25,"style":"fontsize-14"},{"offset":668,"length":63,"style":"fontsize-14"},{"offset":0,"length":34,"style":"fontfamily-sans-serif"},{"offset":35,"length":24,"style":"fontfamily-sans-serif"},{"offset":60,"length":55,"style":"fontfamily-sans-serif"},{"offset":116,"length":8,"style":"fontfamily-sans-serif"},{"offset":125,"length":3,"style":"fontfamily-sans-serif"},{"offset":129,"length":21,"style":"fontfamily-sans-serif"},{"offset":151,"length":103,"style":"fontfamily-sans-serif"},{"offset":255,"length":86,"style":"fontfamily-sans-serif"},{"offset":342,"length":70,"style":"fontfamily-sans-serif"},{"offset":413,"length":40,"style":"fontfamily-sans-serif"},{"offset":454,"length":8,"style":"fontfamily-sans-serif"},{"offset":463,"length":71,"style":"fontfamily-sans-serif"},{"offset":535,"length":12,"style":"fontfamily-sans-serif"},{"offset":548,"length":15,"style":"fontfamily-sans-serif"},{"offset":564,"length":28,"style":"fontfamily-sans-serif"},{"offset":593,"length":13,"style":"fontfamily-sans-serif"},{"offset":607,"length":34,"style":"fontfamily-sans-serif"},{"offset":642,"length":25,"style":"fontfamily-sans-serif"},{"offset":668,"length":63,"style":"fontfamily-sans-serif"},{"offset":35,"length":24,"style":"color-rgb(51,102,204)"},{"offset":116,"length":8,"style":"color-rgb(51,102,204)"},{"offset":129,"length":21,"style":"color-rgb(51,102,204)"},{"offset":246,"length":8,"style":"color-rgb(51,102,204)"},{"offset":342,"length":7,"style":"color-rgb(51,102,204)"},{"offset":408,"length":4,"style":"color-rgb(51,102,204)"},{"offset":454,"length":8,"style":"color-rgb(51,102,204)"},{"offset":530,"length":4,"style":"color-rgb(51,102,204)"},{"offset":548,"length":15,"style":"color-rgb(51,102,204)"},{"offset":593,"length":13,"style":"color-rgb(51,102,204)"},{"offset":642,"length":16,"style":"color-rgb(51,102,204)"},{"offset":659,"length":8,"style":"color-rgb(51,102,204)"},{"offset":727,"length":4,"style":"color-rgb(51,102,204)"},{"offset":35,"length":24,"style":"bgcolor-initial"},{"offset":116,"length":8,"style":"bgcolor-initial"},{"offset":129,"length":21,"style":"bgcolor-initial"},{"offset":246,"length":8,"style":"bgcolor-initial"},{"offset":342,"length":7,"style":"bgcolor-initial"},{"offset":408,"length":4,"style":"bgcolor-initial"},{"offset":454,"length":8,"style":"bgcolor-initial"},{"offset":530,"length":4,"style":"bgcolor-initial"},{"offset":548,"length":15,"style":"bgcolor-initial"},{"offset":593,"length":13,"style":"bgcolor-initial"},{"offset":642,"length":16,"style":"bgcolor-initial"},{"offset":659,"length":8,"style":"bgcolor-initial"},{"offset":727,"length":4,"style":"bgcolor-initial"},{"offset":55,"length":4,"style":"SUPERSCRIPT"},{"offset":246,"length":8,"style":"SUPERSCRIPT"},{"offset":408,"length":4,"style":"SUPERSCRIPT"},{"offset":530,"length":4,"style":"SUPERSCRIPT"},{"offset":602,"length":4,"style":"SUPERSCRIPT"},{"offset":659,"length":8,"style":"SUPERSCRIPT"},{"offset":727,"length":4,"style":"SUPERSCRIPT"}],"entityRanges":[{"offset":35,"length":20,"key":18},{"offset":55,"length":4,"key":19},{"offset":116,"length":8,"key":20},{"offset":129,"length":21,"key":21},{"offset":246,"length":4,"key":22},{"offset":250,"length":4,"key":23},{"offset":342,"length":7,"key":24},{"offset":408,"length":4,"key":25},{"offset":454,"length":8,"key":26},{"offset":530,"length":4,"key":27},{"offset":548,"length":15,"key":28},{"offset":593,"length":9,"key":29},{"offset":602,"length":4,"key":30},{"offset":642,"length":16,"key":31},{"offset":659,"length":4,"key":32},{"offset":663,"length":4,"key":33},{"offset":727,"length":4,"key":34}],"data":{"text-align":"start"}},{"key":"2ti6r","text":"The Church mobilized to avenge this defeat. Pope Innocent III issued a bull declaring a crusade against the Livonians.[27] Bishop Albert was proclaimed Bishop of Livonia by his uncle Hartwig of Uthlede, Prince-Archbishop of Bremen and Hamburg in 1199. Albert landed in Riga in 1200[25][27] with 23 ships[28] and 500 Westphalian crusaders.[29] In 1201, he transferred the seat of the Livonian bishopric from Uexküll to Riga, extorting agreement to do this from the elders of Riga by force.[25] ","type":"unstyled","depth":0,"inlineStyleRanges":[{"offset":0,"length":43,"style":"color-rgb(32,33,34)"},{"offset":44,"length":17,"style":"color-rgb(32,33,34)"},{"offset":62,"length":45,"style":"color-rgb(32,33,34)"},{"offset":108,"length":14,"style":"color-rgb(32,33,34)"},{"offset":123,"length":13,"style":"color-rgb(32,33,34)"},{"offset":137,"length":14,"style":"color-rgb(32,33,34)"},{"offset":152,"length":17,"style":"color-rgb(32,33,34)"},{"offset":170,"length":12,"style":"color-rgb(32,33,34)"},{"offset":183,"length":19,"style":"color-rgb(32,33,34)"},{"offset":203,"length":39,"style":"color-rgb(32,33,34)"},{"offset":243,"length":46,"style":"color-rgb(32,33,34)"},{"offset":290,"length":17,"style":"color-rgb(32,33,34)"},{"offset":308,"length":34,"style":"color-rgb(32,33,34)"},{"offset":343,"length":149,"style":"color-rgb(32,33,34)"},{"offset":0,"length":43,"style":"bgcolor-rgb(255,255,255)"},{"offset":44,"length":17,"style":"bgcolor-rgb(255,255,255)"},{"offset":62,"length":45,"style":"bgcolor-rgb(255,255,255)"},{"offset":108,"length":14,"style":"bgcolor-rgb(255,255,255)"},{"offset":123,"length":13,"style":"bgcolor-rgb(255,255,255)"},{"offset":137,"length":14,"style":"bgcolor-rgb(255,255,255)"},{"offset":152,"length":17,"style":"bgcolor-rgb(255,255,255)"},{"offset":170,"length":12,"style":"bgcolor-rgb(255,255,255)"},{"offset":183,"length":19,"style":"bgcolor-rgb(255,255,255)"},{"offset":203,"length":39,"style":"bgcolor-rgb(255,255,255)"},{"offset":243,"length":46,"style":"bgcolor-rgb(255,255,255)"},{"offset":290,"length":17,"style":"bgcolor-rgb(255,255,255)"},{"offset":308,"length":34,"style":"bgcolor-rgb(255,255,255)"},{"offset":343,"length":149,"style":"bgcolor-rgb(255,255,255)"},{"offset":0,"length":43,"style":"fontsize-14"},{"offset":44,"length":17,"style":"fontsize-14"},{"offset":62,"length":45,"style":"fontsize-14"},{"offset":108,"length":14,"style":"fontsize-14"},{"offset":123,"length":13,"style":"fontsize-14"},{"offset":137,"length":14,"style":"fontsize-14"},{"offset":152,"length":17,"style":"fontsize-14"},{"offset":170,"length":12,"style":"fontsize-14"},{"offset":183,"length":19,"style":"fontsize-14"},{"offset":203,"length":39,"style":"fontsize-14"},{"offset":243,"length":46,"style":"fontsize-14"},{"offset":290,"length":17,"style":"fontsize-14"},{"offset":308,"length":34,"style":"fontsize-14"},{"offset":343,"length":149,"style":"fontsize-14"},{"offset":0,"length":43,"style":"fontfamily-sans-serif"},{"offset":44,"length":17,"style":"fontfamily-sans-serif"},{"offset":62,"length":45,"style":"fontfamily-sans-serif"},{"offset":108,"length":14,"style":"fontfamily-sans-serif"},{"offset":123,"length":13,"style":"fontfamily-sans-serif"},{"offset":137,"length":14,"style":"fontfamily-sans-serif"},{"offset":152,"length":17,"style":"fontfamily-sans-serif"},{"offset":170,"length":12,"style":"fontfamily-sans-serif"},{"offset":183,"length":19,"style":"fontfamily-sans-serif"},{"offset":203,"length":39,"style":"fontfamily-sans-serif"},{"offset":243,"length":46,"style":"fontfamily-sans-serif"},{"offset":290,"length":17,"style":"fontfamily-sans-serif"},{"offset":308,"length":34,"style":"fontfamily-sans-serif"},{"offset":343,"length":149,"style":"fontfamily-sans-serif"},{"offset":44,"length":17,"style":"color-rgb(51,102,204)"},{"offset":108,"length":9,"style":"color-rgb(51,102,204)"},{"offset":118,"length":4,"style":"color-rgb(51,102,204)"},{"offset":123,"length":13,"style":"color-rgb(51,102,204)"},{"offset":152,"length":17,"style":"color-rgb(51,102,204)"},{"offset":183,"length":18,"style":"color-rgb(51,102,204)"},{"offset":203,"length":39,"style":"color-rgb(51,102,204)"},{"offset":281,"length":8,"style":"color-rgb(51,102,204)"},{"offset":303,"length":4,"style":"color-rgb(51,102,204)"},{"offset":338,"length":4,"style":"color-rgb(51,102,204)"},{"offset":488,"length":4,"style":"color-rgb(51,102,204)"},{"offset":44,"length":17,"style":"bgcolor-initial"},{"offset":108,"length":9,"style":"bgcolor-initial"},{"offset":118,"length":4,"style":"bgcolor-initial"},{"offset":123,"length":13,"style":"bgcolor-initial"},{"offset":152,"length":17,"style":"bgcolor-initial"},{"offset":183,"length":18,"style":"bgcolor-initial"},{"offset":203,"length":39,"style":"bgcolor-initial"},{"offset":281,"length":8,"style":"bgcolor-initial"},{"offset":303,"length":4,"style":"bgcolor-initial"},{"offset":338,"length":4,"style":"bgcolor-initial"},{"offset":488,"length":4,"style":"bgcolor-initial"},{"offset":118,"length":4,"style":"SUPERSCRIPT"},{"offset":281,"length":8,"style":"SUPERSCRIPT"},{"offset":303,"length":4,"style":"SUPERSCRIPT"},{"offset":338,"length":4,"style":"SUPERSCRIPT"},{"offset":488,"length":4,"style":"SUPERSCRIPT"}],"entityRanges":[{"offset":44,"length":17,"key":35},{"offset":108,"length":9,"key":36},{"offset":118,"length":4,"key":37},{"offset":123,"length":13,"key":38},{"offset":152,"length":17,"key":39},{"offset":183,"length":18,"key":40},{"offset":203,"length":39,"key":41},{"offset":281,"length":4,"key":42},{"offset":285,"length":4,"key":43},{"offset":303,"length":4,"key":44},{"offset":338,"length":4,"key":45},{"offset":488,"length":4,"key":46}],"data":{}}],"entityMap":{"0":{"type":"LINK","mutability":"MUTABLE","data":{"url":"https://en.wikipedia.org/wiki/Daugava","title":"Daugava","targetOption":"","_map":{"type":"LINK","mutability":"MUTABLE","data":{"url":"https://en.wikipedia.org/wiki/Daugava","title":"Daugava","targetOption":""}}}},"1":{"type":"LINK","mutability":"MUTABLE","data":{"url":"https://en.wikipedia.org/wiki/Trade_route","title":"trade route","targetOption":"","_map":{"type":"LINK","mutability":"MUTABLE","data":{"url":"https://en.wikipedia.org/wiki/Trade_route","title":"trade route","targetOption":""}}}},"2":{"type":"LINK","mutability":"MUTABLE","data":{"url":"https://en.wikipedia.org/wiki/Varangians","title":"Vikings'","targetOption":"","_map":{"type":"LINK","mutability":"MUTABLE","data":{"url":"https://en.wikipedia.org/wiki/Varangians","title":"Vikings'","targetOption":""}}}},"3":{"type":"LINK","mutability":"MUTABLE","data":{"url":"https://en.wikipedia.org/wiki/Route_from_the_Varangians_to_the_Greeks","title":"Dvina–Dnieper navigation route","targetOption":"","_map":{"type":"LINK","mutability":"MUTABLE","data":{"url":"https://en.wikipedia.org/wiki/Route_from_the_Varangians_to_the_Greeks","title":"Dvina–Dnieper navigation route","targetOption":""}}}},"4":{"type":"LINK","mutability":"MUTABLE","data":{"url":"https://en.wikipedia.org/wiki/Riga#cite_note-BilmanisLIS-25","title":"[25]","targetOption":"","_map":{"type":"LINK","mutability":"MUTABLE","data":{"url":"https://en.wikipedia.org/wiki/Riga#cite_note-BilmanisLIS-25","title":"[25]","targetOption":""}}}},"5":{"type":"LINK","mutability":"MUTABLE","data":{"url":"https://en.wikipedia.org/wiki/Natural_harbour","title":"natural harbor","targetOption":"","_map":{"type":"LINK","mutability":"MUTABLE","data":{"url":"https://en.wikipedia.org/wiki/Natural_harbour","title":"natural harbor","targetOption":""}}}},"6":{"type":"LINK","mutability":"MUTABLE","data":{"url":"https://en.wikipedia.org/wiki/Riga#cite_note-BilmanisLIS-25","title":"[25]","targetOption":"","_map":{"type":"LINK","mutability":"MUTABLE","data":{"url":"https://en.wikipedia.org/wiki/Riga#cite_note-BilmanisLIS-25","title":"[25]","targetOption":""}}}},"7":{"type":"LINK","mutability":"MUTABLE","data":{"url":"https://en.wikipedia.org/wiki/Livonians","title":"Livs","targetOption":"","_map":{"type":"LINK","mutability":"MUTABLE","data":{"url":"https://en.wikipedia.org/wiki/Livonians","title":"Livs","targetOption":""}}}},"8":{"type":"LINK","mutability":"MUTABLE","data":{"url":"https://en.wikipedia.org/wiki/Baltic_Finnic_peoples","title":"Finnic","targetOption":"","_map":{"type":"LINK","mutability":"MUTABLE","data":{"url":"https://en.wikipedia.org/wiki/Baltic_Finnic_peoples","title":"Finnic","targetOption":""}}}},"9":{"type":"IMAGE","mutability":"MUTABLE","data":{"src":"https://upload.wikimedia.org/wikipedia/commons/thumb/2/24/Plaza_del_Ayuntamiento%2C_Riga%2C_Letonia%2C_2012-08-07%2C_DD_10.JPG/220px-Plaza_del_Ayuntamiento%2C_Riga%2C_Letonia%2C_2012-08-07%2C_DD_10.JPG","alt":"","height":"","width":"","_map":{"type":"IMAGE","mutability":"MUTABLE","data":{"src":"https://upload.wikimedia.org/wikipedia/commons/thumb/2/24/Plaza_del_Ayuntamiento%2C_Riga%2C_Letonia%2C_2012-08-07%2C_DD_10.JPG/220px-Plaza_del_Ayuntamiento%2C_Riga%2C_Letonia%2C_2012-08-07%2C_DD_10.JPG","alt":"","height":"","width":""}}}},"10":{"type":"LINK","mutability":"MUTABLE","data":{"url":"https://en.wikipedia.org/wiki/House_of_the_Blackheads_(Riga)","title":"building of the Brotherhood of Blackheads","targetOption":"","_map":{"type":"LINK","mutability":"MUTABLE","data":{"url":"https://en.wikipedia.org/wiki/House_of_the_Blackheads_(Riga)","title":"building of the Brotherhood of Blackheads","targetOption":""}}}},"11":{"type":"LINK","mutability":"MUTABLE","data":{"url":"https://en.wikipedia.org/wiki/Vecr%C4%ABga","title":"Vecrīga","targetOption":"","_map":{"type":"LINK","mutability":"MUTABLE","data":{"url":"https://en.wikipedia.org/wiki/Vecr%C4%ABga","title":"Vecrīga","targetOption":""}}}},"12":{"type":"LINK","mutability":"MUTABLE","data":{"url":"https://en.wikipedia.org/wiki/Viking_Age","title":"Viking trade during the early Middle Ages","targetOption":"","_map":{"type":"LINK","mutability":"MUTABLE","data":{"url":"https://en.wikipedia.org/wiki/Viking_Age","title":"Viking trade during the early Middle Ages","targetOption":""}}}},"13":{"type":"LINK","mutability":"MUTABLE","data":{"url":"https://en.wikipedia.org/wiki/Riga#cite_note-BilmanisLIS-25","title":"[25]","targetOption":"","_map":{"type":"LINK","mutability":"MUTABLE","data":{"url":"https://en.wikipedia.org/wiki/Riga#cite_note-BilmanisLIS-25","title":"[25]","targetOption":""}}}},"14":{"type":"LINK","mutability":"MUTABLE","data":{"url":"https://en.wikipedia.org/wiki/Animal_husbandry","title":"animal husbandry","targetOption":"","_map":{"type":"LINK","mutability":"MUTABLE","data":{"url":"https://en.wikipedia.org/wiki/Animal_husbandry","title":"animal husbandry","targetOption":""}}}},"15":{"type":"LINK","mutability":"MUTABLE","data":{"url":"https://en.wikipedia.org/wiki/Riga#cite_note-BilmanisLIS-25","title":"[25]","targetOption":"","_map":{"type":"LINK","mutability":"MUTABLE","data":{"url":"https://en.wikipedia.org/wiki/Riga#cite_note-BilmanisLIS-25","title":"[25]","targetOption":""}}}},"16":{"type":"LINK","mutability":"MUTABLE","data":{"url":"https://en.wikipedia.org/wiki/Livonian_Chronicle_of_Henry","title":"Livonian Chronicle of Henry","targetOption":"","_map":{"type":"LINK","mutability":"MUTABLE","data":{"url":"https://en.wikipedia.org/wiki/Livonian_Chronicle_of_Henry","title":"Livonian Chronicle of Henry","targetOption":""}}}},"17":{"type":"LINK","mutability":"MUTABLE","data":{"url":"https://en.wikipedia.org/wiki/Riga#cite_note-BilmanisLIS-25","title":"[25]","targetOption":"","_map":{"type":"LINK","mutability":"MUTABLE","data":{"url":"https://en.wikipedia.org/wiki/Riga#cite_note-BilmanisLIS-25","title":"[25]","targetOption":""}}}},"18":{"type":"LINK","mutability":"MUTABLE","data":{"url":"https://en.wikipedia.org/wiki/Saint_Meinhard","title":"Meinhard of Segeberg","targetOption":"","_map":{"type":"LINK","mutability":"MUTABLE","data":{"url":"https://en.wikipedia.org/wiki/Saint_Meinhard","title":"Meinhard of Segeberg","targetOption":""}}}},"19":{"type":"LINK","mutability":"MUTABLE","data":{"url":"https://en.wikipedia.org/wiki/Riga#cite_note-EMA-26","title":"[26]","targetOption":"","_map":{"type":"LINK","mutability":"MUTABLE","data":{"url":"https://en.wikipedia.org/wiki/Riga#cite_note-EMA-26","title":"[26]","targetOption":""}}}},"20":{"type":"LINK","mutability":"MUTABLE","data":{"url":"https://en.wikipedia.org/wiki/Catholic","title":"Catholic","targetOption":"","_map":{"type":"LINK","mutability":"MUTABLE","data":{"url":"https://en.wikipedia.org/wiki/Catholic","title":"Catholic","targetOption":""}}}},"21":{"type":"LINK","mutability":"MUTABLE","data":{"url":"https://en.wikipedia.org/wiki/Eastern_Orthodox_Church","title":"Orthodox Christianity","targetOption":"","_map":{"type":"LINK","mutability":"MUTABLE","data":{"url":"https://en.wikipedia.org/wiki/Eastern_Orthodox_Church","title":"Orthodox Christianity","targetOption":""}}}},"22":{"type":"LINK","mutability":"MUTABLE","data":{"url":"https://en.wikipedia.org/wiki/Riga#cite_note-BilmanisLIS-25","title":"[25]","targetOption":"","_map":{"type":"LINK","mutability":"MUTABLE","data":{"url":"https://en.wikipedia.org/wiki/Riga#cite_note-BilmanisLIS-25","title":"[25]","targetOption":""}}}},"23":{"type":"LINK","mutability":"MUTABLE","data":{"url":"https://en.wikipedia.org/wiki/Riga#cite_note-EMA-26","title":"[26]","targetOption":"","_map":{"type":"LINK","mutability":"MUTABLE","data":{"url":"https://en.wikipedia.org/wiki/Riga#cite_note-EMA-26","title":"[26]","targetOption":""}}}},"24":{"type":"LINK","mutability":"MUTABLE","data":{"url":"https://en.wikipedia.org/wiki/Ik%C5%A1%C4%B7ile","title":"Ikšķile","targetOption":"","_map":{"type":"LINK","mutability":"MUTABLE","data":{"url":"https://en.wikipedia.org/wiki/Ik%C5%A1%C4%B7ile","title":"Ikšķile","targetOption":""}}}},"25":{"type":"LINK","mutability":"MUTABLE","data":{"url":"https://en.wikipedia.org/wiki/Riga#cite_note-EMA-26","title":"[26]","targetOption":"","_map":{"type":"LINK","mutability":"MUTABLE","data":{"url":"https://en.wikipedia.org/wiki/Riga#cite_note-EMA-26","title":"[26]","targetOption":""}}}},"26":{"type":"LINK","mutability":"MUTABLE","data":{"url":"https://en.wikipedia.org/wiki/Paganism","title":"paganism","targetOption":"","_map":{"type":"LINK","mutability":"MUTABLE","data":{"url":"https://en.wikipedia.org/wiki/Paganism","title":"paganism","targetOption":""}}}},"27":{"type":"LINK","mutability":"MUTABLE","data":{"url":"https://en.wikipedia.org/wiki/Riga#cite_note-Saga-27","title":"[27]","targetOption":"","_map":{"type":"LINK","mutability":"MUTABLE","data":{"url":"https://en.wikipedia.org/wiki/Riga#cite_note-Saga-27","title":"[27]","targetOption":""}}}},"28":{"type":"LINK","mutability":"MUTABLE","data":{"url":"https://en.wikipedia.org/wiki/Berthold_of_Hanover","title":"Bishop Berthold","targetOption":"","_map":{"type":"LINK","mutability":"MUTABLE","data":{"url":"https://en.wikipedia.org/wiki/Berthold_of_Hanover","title":"Bishop Berthold","targetOption":""}}}},"29":{"type":"LINK","mutability":"MUTABLE","data":{"url":"https://en.wikipedia.org/wiki/Crusaders","title":"crusaders","targetOption":"","_map":{"type":"LINK","mutability":"MUTABLE","data":{"url":"https://en.wikipedia.org/wiki/Crusaders","title":"crusaders","targetOption":""}}}},"30":{"type":"LINK","mutability":"MUTABLE","data":{"url":"https://en.wikipedia.org/wiki/Riga#cite_note-Saga-27","title":"[27]","targetOption":"","_map":{"type":"LINK","mutability":"MUTABLE","data":{"url":"https://en.wikipedia.org/wiki/Riga#cite_note-Saga-27","title":"[27]","targetOption":""}}}},"31":{"type":"LINK","mutability":"MUTABLE","data":{"url":"https://en.wikipedia.org/wiki/Christianisation","title":"Christianization","targetOption":"","_map":{"type":"LINK","mutability":"MUTABLE","data":{"url":"https://en.wikipedia.org/wiki/Christianisation","title":"Christianization","targetOption":""}}}},"32":{"type":"LINK","mutability":"MUTABLE","data":{"url":"https://en.wikipedia.org/wiki/Riga#cite_note-BilmanisLIS-25","title":"[25]","targetOption":"","_map":{"type":"LINK","mutability":"MUTABLE","data":{"url":"https://en.wikipedia.org/wiki/Riga#cite_note-BilmanisLIS-25","title":"[25]","targetOption":""}}}},"33":{"type":"LINK","mutability":"MUTABLE","data":{"url":"https://en.wikipedia.org/wiki/Riga#cite_note-EMA-26","title":"[26]","targetOption":"","_map":{"type":"LINK","mutability":"MUTABLE","data":{"url":"https://en.wikipedia.org/wiki/Riga#cite_note-EMA-26","title":"[26]","targetOption":""}}}},"34":{"type":"LINK","mutability":"MUTABLE","data":{"url":"https://en.wikipedia.org/wiki/Riga#cite_note-Saga-27","title":"[27]","targetOption":"","_map":{"type":"LINK","mutability":"MUTABLE","data":{"url":"https://en.wikipedia.org/wiki/Riga#cite_note-Saga-27","title":"[27]","targetOption":""}}}},"35":{"type":"LINK","mutability":"MUTABLE","data":{"url":"https://en.wikipedia.org/wiki/Pope_Innocent_III","title":"Pope Innocent III","targetOption":"","_map":{"type":"LINK","mutability":"MUTABLE","data":{"url":"https://en.wikipedia.org/wiki/Pope_Innocent_III","title":"Pope Innocent III","targetOption":""}}}},"36":{"type":"LINK","mutability":"MUTABLE","data":{"url":"https://en.wikipedia.org/wiki/Livonians","title":"Livonians","targetOption":"","_map":{"type":"LINK","mutability":"MUTABLE","data":{"url":"https://en.wikipedia.org/wiki/Livonians","title":"Livonians","targetOption":""}}}},"37":{"type":"LINK","mutability":"MUTABLE","data":{"url":"https://en.wikipedia.org/wiki/Riga#cite_note-Saga-27","title":"[27]","targetOption":"","_map":{"type":"LINK","mutability":"MUTABLE","data":{"url":"https://en.wikipedia.org/wiki/Riga#cite_note-Saga-27","title":"[27]","targetOption":""}}}},"38":{"type":"LINK","mutability":"MUTABLE","data":{"url":"https://en.wikipedia.org/wiki/Albert_of_Riga","title":"Bishop Albert","targetOption":"","_map":{"type":"LINK","mutability":"MUTABLE","data":{"url":"https://en.wikipedia.org/wiki/Albert_of_Riga","title":"Bishop Albert","targetOption":""}}}},"39":{"type":"LINK","mutability":"MUTABLE","data":{"url":"https://en.wikipedia.org/wiki/Bishop_of_Livonia","title":"Bishop of Livonia","targetOption":"","_map":{"type":"LINK","mutability":"MUTABLE","data":{"url":"https://en.wikipedia.org/wiki/Bishop_of_Livonia","title":"Bishop of Livonia","targetOption":""}}}},"40":{"type":"LINK","mutability":"MUTABLE","data":{"url":"https://en.wikipedia.org/wiki/Hartwig_of_Uthlede","title":"Hartwig of Uthlede","targetOption":"","_map":{"type":"LINK","mutability":"MUTABLE","data":{"url":"https://en.wikipedia.org/wiki/Hartwig_of_Uthlede","title":"Hartwig of Uthlede","targetOption":""}}}},"41":{"type":"LINK","mutability":"MUTABLE","data":{"url":"https://en.wikipedia.org/wiki/Prince-Archbishopric_of_Bremen","title":"Prince-Archbishop of Bremen and Hamburg","targetOption":"","_map":{"type":"LINK","mutability":"MUTABLE","data":{"url":"https://en.wikipedia.org/wiki/Prince-Archbishopric_of_Bremen","title":"Prince-Archbishop of Bremen and Hamburg","targetOption":""}}}},"42":{"type":"LINK","mutability":"MUTABLE","data":{"url":"https://en.wikipedia.org/wiki/Riga#cite_note-BilmanisLIS-25","title":"[25]","targetOption":"","_map":{"type":"LINK","mutability":"MUTABLE","data":{"url":"https://en.wikipedia.org/wiki/Riga#cite_note-BilmanisLIS-25","title":"[25]","targetOption":""}}}},"43":{"type":"LINK","mutability":"MUTABLE","data":{"url":"https://en.wikipedia.org/wiki/Riga#cite_note-Saga-27","title":"[27]","targetOption":"","_map":{"type":"LINK","mutability":"MUTABLE","data":{"url":"https://en.wikipedia.org/wiki/Riga#cite_note-Saga-27","title":"[27]","targetOption":""}}}},"44":{"type":"LINK","mutability":"MUTABLE","data":{"url":"https://en.wikipedia.org/wiki/Riga#cite_note-CathE-28","title":"[28]","targetOption":"","_map":{"type":"LINK","mutability":"MUTABLE","data":{"url":"https://en.wikipedia.org/wiki/Riga#cite_note-CathE-28","title":"[28]","targetOption":""}}}},"45":{"type":"LINK","mutability":"MUTABLE","data":{"url":"https://en.wikipedia.org/wiki/Riga#cite_note-ReferenceA-29","title":"[29]","targetOption":"","_map":{"type":"LINK","mutability":"MUTABLE","data":{"url":"https://en.wikipedia.org/wiki/Riga#cite_note-ReferenceA-29","title":"[29]","targetOption":""}}}},"46":{"type":"LINK","mutability":"MUTABLE","data":{"url":"https://en.wikipedia.org/wiki/Riga#cite_note-BilmanisLIS-25","title":"[25]","targetOption":"","_map":{"type":"LINK","mutability":"MUTABLE","data":{"url":"https://en.wikipedia.org/wiki/Riga#cite_note-BilmanisLIS-25","title":"[25]","targetOption":""}}}}}},"sidebar":{"blocks":[{"key":"h8ds","text":"Under Bishop Albert","type":"header-two","depth":0,"inlineStyleRanges":[{"offset":0,"length":19,"style":"color-rgb(0,0,0)"},{"offset":0,"length":19,"style":"bgcolor-rgb(255,255,255)"},{"offset":0,"length":19,"style":"fontsize-1.2em"},{"offset":0,"length":19,"style":"fontfamily-sans-serif"},{"offset":0,"length":19,"style":"BOLD"}],"entityRanges":[],"data":{"text-align":"start"}},{"key":"9bm05","text":"The year 1201 also marked the first arrival of German merchants in Novgorod, via the Dvina.[30] To defend territory[31] and trade, Albert established the Order of Livonian Brothers of the Sword in 1202, which was open to nobles and merchants.[30]","type":"unstyled","depth":0,"inlineStyleRanges":[{"offset":0,"length":95,"style":"color-rgb(32,33,34)"},{"offset":96,"length":23,"style":"color-rgb(32,33,34)"},{"offset":120,"length":33,"style":"color-rgb(32,33,34)"},{"offset":154,"length":39,"style":"color-rgb(32,33,34)"},{"offset":194,"length":52,"style":"color-rgb(32,33,34)"},{"offset":0,"length":95,"style":"bgcolor-rgb(255,255,255)"},{"offset":96,"length":23,"style":"bgcolor-rgb(255,255,255)"},{"offset":120,"length":33,"style":"bgcolor-rgb(255,255,255)"},{"offset":154,"length":39,"style":"bgcolor-rgb(255,255,255)"},{"offset":194,"length":52,"style":"bgcolor-rgb(255,255,255)"},{"offset":0,"length":95,"style":"fontsize-14"},{"offset":96,"length":23,"style":"fontsize-14"},{"offset":120,"length":33,"style":"fontsize-14"},{"offset":154,"length":39,"style":"fontsize-14"},{"offset":194,"length":52,"style":"fontsize-14"},{"offset":0,"length":95,"style":"fontfamily-sans-serif"},{"offset":96,"length":23,"style":"fontfamily-sans-serif"},{"offset":120,"length":33,"style":"fontfamily-sans-serif"},{"offset":154,"length":39,"style":"fontfamily-sans-serif"},{"offset":194,"length":52,"style":"fontfamily-sans-serif"},{"offset":91,"length":4,"style":"SUPERSCRIPT"},{"offset":115,"length":4,"style":"SUPERSCRIPT"},{"offset":242,"length":4,"style":"SUPERSCRIPT"},{"offset":91,"length":4,"style":"color-rgb(51,102,204)"},{"offset":115,"length":4,"style":"color-rgb(51,102,204)"},{"offset":154,"length":39,"style":"color-rgb(51,102,204)"},{"offset":242,"length":4,"style":"color-rgb(51,102,204)"},{"offset":91,"length":4,"style":"bgcolor-initial"},{"offset":115,"length":4,"style":"bgcolor-initial"},{"offset":154,"length":39,"style":"bgcolor-initial"},{"offset":242,"length":4,"style":"bgcolor-initial"}],"entityRanges":[{"offset":91,"length":4,"key":0},{"offset":115,"length":4,"key":1},{"offset":154,"length":39,"key":2},{"offset":242,"length":4,"key":3}],"data":{"text-align":"start"}},{"key":"74vbi","text":"The Christianisation of the Livs continued. In 1207, Albert started to fortify the town.[30][32] Emperor Philip invested Albert with Livonia as a fief[33] and principality of the Holy Roman Empire.[25] To promote a permanent military presence, territorial ownership was divided between the Church and the Order, with the Church taking Riga and two-thirds of all lands conquered and granting the Order a third.[34] Until then, it had been customary for crusaders to serve for a year and then return home.[34]","type":"unstyled","depth":0,"inlineStyleRanges":[{"offset":0,"length":96,"style":"color-rgb(32,33,34)"},{"offset":97,"length":14,"style":"color-rgb(32,33,34)"},{"offset":112,"length":42,"style":"color-rgb(32,33,34)"},{"offset":155,"length":23,"style":"color-rgb(32,33,34)"},{"offset":179,"length":22,"style":"color-rgb(32,33,34)"},{"offset":202,"length":102,"style":"color-rgb(32,33,34)"},{"offset":305,"length":89,"style":"color-rgb(32,33,34)"},{"offset":395,"length":5,"style":"color-rgb(32,33,34)"},{"offset":401,"length":12,"style":"color-rgb(32,33,34)"},{"offset":414,"length":93,"style":"color-rgb(32,33,34)"},{"offset":0,"length":96,"style":"bgcolor-rgb(255,255,255)"},{"offset":97,"length":14,"style":"bgcolor-rgb(255,255,255)"},{"offset":112,"length":42,"style":"bgcolor-rgb(255,255,255)"},{"offset":155,"length":23,"style":"bgcolor-rgb(255,255,255)"},{"offset":179,"length":22,"style":"bgcolor-rgb(255,255,255)"},{"offset":202,"length":102,"style":"bgcolor-rgb(255,255,255)"},{"offset":305,"length":89,"style":"bgcolor-rgb(255,255,255)"},{"offset":395,"length":5,"style":"bgcolor-rgb(255,255,255)"},{"offset":401,"length":12,"style":"bgcolor-rgb(255,255,255)"},{"offset":414,"length":93,"style":"bgcolor-rgb(255,255,255)"},{"offset":0,"length":96,"style":"fontsize-14"},{"offset":97,"length":14,"style":"fontsize-14"},{"offset":112,"length":42,"style":"fontsize-14"},{"offset":155,"length":23,"style":"fontsize-14"},{"offset":179,"length":22,"style":"fontsize-14"},{"offset":202,"length":102,"style":"fontsize-14"},{"offset":305,"length":89,"style":"fontsize-14"},{"offset":395,"length":5,"style":"fontsize-14"},{"offset":401,"length":12,"style":"fontsize-14"},{"offset":414,"length":93,"style":"fontsize-14"},{"offset":0,"length":96,"style":"fontfamily-sans-serif"},{"offset":97,"length":14,"style":"fontfamily-sans-serif"},{"offset":112,"length":42,"style":"fontfamily-sans-serif"},{"offset":155,"length":23,"style":"fontfamily-sans-serif"},{"offset":179,"length":22,"style":"fontfamily-sans-serif"},{"offset":202,"length":102,"style":"fontfamily-sans-serif"},{"offset":305,"length":89,"style":"fontfamily-sans-serif"},{"offset":395,"length":5,"style":"fontfamily-sans-serif"},{"offset":401,"length":12,"style":"fontfamily-sans-serif"},{"offset":414,"length":93,"style":"fontfamily-sans-serif"},{"offset":88,"length":8,"style":"SUPERSCRIPT"},{"offset":150,"length":4,"style":"SUPERSCRIPT"},{"offset":197,"length":4,"style":"SUPERSCRIPT"},{"offset":409,"length":4,"style":"SUPERSCRIPT"},{"offset":503,"length":4,"style":"SUPERSCRIPT"},{"offset":88,"length":8,"style":"color-rgb(51,102,204)"},{"offset":97,"length":14,"style":"color-rgb(51,102,204)"},{"offset":150,"length":4,"style":"color-rgb(51,102,204)"},{"offset":179,"length":17,"style":"color-rgb(51,102,204)"},{"offset":197,"length":4,"style":"color-rgb(51,102,204)"},{"offset":409,"length":4,"style":"color-rgb(51,102,204)"},{"offset":503,"length":4,"style":"color-rgb(51,102,204)"},{"offset":88,"length":8,"style":"bgcolor-initial"},{"offset":97,"length":14,"style":"bgcolor-initial"},{"offset":150,"length":4,"style":"bgcolor-initial"},{"offset":179,"length":17,"style":"bgcolor-initial"},{"offset":197,"length":4,"style":"bgcolor-initial"},{"offset":409,"length":4,"style":"bgcolor-initial"},{"offset":503,"length":4,"style":"bgcolor-initial"}],"entityRanges":[{"offset":88,"length":4,"key":4},{"offset":92,"length":4,"key":5},{"offset":97,"length":14,"key":6},{"offset":150,"length":4,"key":7},{"offset":179,"length":17,"key":8},{"offset":197,"length":4,"key":9},{"offset":409,"length":4,"key":10},{"offset":503,"length":4,"key":11}],"data":{"text-align":"start"}},{"key":"92utg","text":"Albert had ensured Riga's commercial future by obtaining papal bulls which decreed that all German merchants had to carry on their Baltic trade through Riga.[34] In 1211, Riga minted its first coinage,[25] and Albert laid the cornerstone for the Riga Dom.[35] Riga was not yet secure as an alliance of tribes failed to take Riga.[34] In 1212, Albert led a campaign to compel Polotsk to grant German merchants free river passage.[30] Polotsk conceded Kukenois (Koknese) and Jersika to Albert, also ending the Livs' tribute to Polotsk.[36]","type":"unstyled","depth":0,"inlineStyleRanges":[{"offset":0,"length":161,"style":"color-rgb(32,33,34)"},{"offset":162,"length":43,"style":"color-rgb(32,33,34)"},{"offset":206,"length":39,"style":"color-rgb(32,33,34)"},{"offset":246,"length":13,"style":"color-rgb(32,33,34)"},{"offset":260,"length":73,"style":"color-rgb(32,33,34)"},{"offset":334,"length":40,"style":"color-rgb(32,33,34)"},{"offset":375,"length":7,"style":"color-rgb(32,33,34)"},{"offset":383,"length":49,"style":"color-rgb(32,33,34)"},{"offset":433,"length":39,"style":"color-rgb(32,33,34)"},{"offset":473,"length":7,"style":"color-rgb(32,33,34)"},{"offset":481,"length":56,"style":"color-rgb(32,33,34)"},{"offset":0,"length":161,"style":"bgcolor-rgb(255,255,255)"},{"offset":162,"length":43,"style":"bgcolor-rgb(255,255,255)"},{"offset":206,"length":39,"style":"bgcolor-rgb(255,255,255)"},{"offset":246,"length":13,"style":"bgcolor-rgb(255,255,255)"},{"offset":260,"length":73,"style":"bgcolor-rgb(255,255,255)"},{"offset":334,"length":40,"style":"bgcolor-rgb(255,255,255)"},{"offset":375,"length":7,"style":"bgcolor-rgb(255,255,255)"},{"offset":383,"length":49,"style":"bgcolor-rgb(255,255,255)"},{"offset":433,"length":39,"style":"bgcolor-rgb(255,255,255)"},{"offset":473,"length":7,"style":"bgcolor-rgb(255,255,255)"},{"offset":481,"length":56,"style":"bgcolor-rgb(255,255,255)"},{"offset":0,"length":161,"style":"fontsize-14"},{"offset":162,"length":43,"style":"fontsize-14"},{"offset":206,"length":39,"style":"fontsize-14"},{"offset":246,"length":13,"style":"fontsize-14"},{"offset":260,"length":73,"style":"fontsize-14"},{"offset":334,"length":40,"style":"fontsize-14"},{"offset":375,"length":7,"style":"fontsize-14"},{"offset":383,"length":49,"style":"fontsize-14"},{"offset":433,"length":39,"style":"fontsize-14"},{"offset":473,"length":7,"style":"fontsize-14"},{"offset":481,"length":56,"style":"fontsize-14"},{"offset":0,"length":161,"style":"fontfamily-sans-serif"},{"offset":162,"length":43,"style":"fontfamily-sans-serif"},{"offset":206,"length":39,"style":"fontfamily-sans-serif"},{"offset":246,"length":13,"style":"fontfamily-sans-serif"},{"offset":260,"length":73,"style":"fontfamily-sans-serif"},{"offset":334,"length":40,"style":"fontfamily-sans-serif"},{"offset":375,"length":7,"style":"fontfamily-sans-serif"},{"offset":383,"length":49,"style":"fontfamily-sans-serif"},{"offset":433,"length":39,"style":"fontfamily-sans-serif"},{"offset":473,"length":7,"style":"fontfamily-sans-serif"},{"offset":481,"length":56,"style":"fontfamily-sans-serif"},{"offset":157,"length":4,"style":"SUPERSCRIPT"},{"offset":201,"length":4,"style":"SUPERSCRIPT"},{"offset":255,"length":4,"style":"SUPERSCRIPT"},{"offset":329,"length":4,"style":"SUPERSCRIPT"},{"offset":428,"length":4,"style":"SUPERSCRIPT"},{"offset":533,"length":4,"style":"SUPERSCRIPT"},{"offset":157,"length":4,"style":"color-rgb(51,102,204)"},{"offset":201,"length":4,"style":"color-rgb(51,102,204)"},{"offset":246,"length":8,"style":"color-rgb(51,102,204)"},{"offset":255,"length":4,"style":"color-rgb(51,102,204)"},{"offset":329,"length":4,"style":"color-rgb(51,102,204)"},{"offset":375,"length":7,"style":"color-rgb(51,102,204)"},{"offset":428,"length":4,"style":"color-rgb(51,102,204)"},{"offset":460,"length":7,"style":"color-rgb(51,102,204)"},{"offset":473,"length":7,"style":"color-rgb(51,102,204)"},{"offset":533,"length":4,"style":"color-rgb(51,102,204)"},{"offset":157,"length":4,"style":"bgcolor-initial"},{"offset":201,"length":4,"style":"bgcolor-initial"},{"offset":246,"length":8,"style":"bgcolor-initial"},{"offset":255,"length":4,"style":"bgcolor-initial"},{"offset":329,"length":4,"style":"bgcolor-initial"},{"offset":375,"length":7,"style":"bgcolor-initial"},{"offset":428,"length":4,"style":"bgcolor-initial"},{"offset":460,"length":7,"style":"bgcolor-initial"},{"offset":473,"length":7,"style":"bgcolor-initial"},{"offset":533,"length":4,"style":"bgcolor-initial"}],"entityRanges":[{"offset":157,"length":4,"key":12},{"offset":201,"length":4,"key":13},{"offset":246,"length":8,"key":14},{"offset":255,"length":4,"key":15},{"offset":329,"length":4,"key":16},{"offset":375,"length":7,"key":17},{"offset":428,"length":4,"key":18},{"offset":460,"length":7,"key":19},{"offset":473,"length":7,"key":20},{"offset":533,"length":4,"key":21}],"data":{"text-align":"start"}}],"entityMap":{"0":{"type":"LINK","mutability":"MUTABLE","data":{"url":"https://en.wikipedia.org/wiki/Riga#cite_note-PDIntBus-30","title":"[30]","targetOption":"","_map":{"type":"LINK","mutability":"MUTABLE","data":{"url":"https://en.wikipedia.org/wiki/Riga#cite_note-PDIntBus-30","title":"[30]","targetOption":""}}}},"1":{"type":"LINK","mutability":"MUTABLE","data":{"url":"https://en.wikipedia.org/wiki/Riga#cite_note-RRiga-31","title":"[31]","targetOption":"","_map":{"type":"LINK","mutability":"MUTABLE","data":{"url":"https://en.wikipedia.org/wiki/Riga#cite_note-RRiga-31","title":"[31]","targetOption":""}}}},"2":{"type":"LINK","mutability":"MUTABLE","data":{"url":"https://en.wikipedia.org/wiki/Livonian_Brothers_of_the_Sword","title":"Order of Livonian Brothers of the Sword","targetOption":"","_map":{"type":"LINK","mutability":"MUTABLE","data":{"url":"https://en.wikipedia.org/wiki/Livonian_Brothers_of_the_Sword","title":"Order of Livonian Brothers of the Sword","targetOption":""}}}},"3":{"type":"LINK","mutability":"MUTABLE","data":{"url":"https://en.wikipedia.org/wiki/Riga#cite_note-PDIntBus-30","title":"[30]","targetOption":"","_map":{"type":"LINK","mutability":"MUTABLE","data":{"url":"https://en.wikipedia.org/wiki/Riga#cite_note-PDIntBus-30","title":"[30]","targetOption":""}}}},"4":{"type":"LINK","mutability":"MUTABLE","data":{"url":"https://en.wikipedia.org/wiki/Riga#cite_note-PDIntBus-30","title":"[30]","targetOption":"","_map":{"type":"LINK","mutability":"MUTABLE","data":{"url":"https://en.wikipedia.org/wiki/Riga#cite_note-PDIntBus-30","title":"[30]","targetOption":""}}}},"5":{"type":"LINK","mutability":"MUTABLE","data":{"url":"https://en.wikipedia.org/wiki/Riga#cite_note-ORZarina-32","title":"[32]","targetOption":"","_map":{"type":"LINK","mutability":"MUTABLE","data":{"url":"https://en.wikipedia.org/wiki/Riga#cite_note-ORZarina-32","title":"[32]","targetOption":""}}}},"6":{"type":"LINK","mutability":"MUTABLE","data":{"url":"https://en.wikipedia.org/wiki/Philip_of_Swabia","title":"Emperor Philip","targetOption":"","_map":{"type":"LINK","mutability":"MUTABLE","data":{"url":"https://en.wikipedia.org/wiki/Philip_of_Swabia","title":"Emperor Philip","targetOption":""}}}},"7":{"type":"LINK","mutability":"MUTABLE","data":{"url":"https://en.wikipedia.org/wiki/Riga#cite_note-HistChristCh-33","title":"[33]","targetOption":"","_map":{"type":"LINK","mutability":"MUTABLE","data":{"url":"https://en.wikipedia.org/wiki/Riga#cite_note-HistChristCh-33","title":"[33]","targetOption":""}}}},"8":{"type":"LINK","mutability":"MUTABLE","data":{"url":"https://en.wikipedia.org/wiki/Holy_Roman_Empire","title":"Holy Roman Empire","targetOption":"","_map":{"type":"LINK","mutability":"MUTABLE","data":{"url":"https://en.wikipedia.org/wiki/Holy_Roman_Empire","title":"Holy Roman Empire","targetOption":""}}}},"9":{"type":"LINK","mutability":"MUTABLE","data":{"url":"https://en.wikipedia.org/wiki/Riga#cite_note-BilmanisLIS-25","title":"[25]","targetOption":"","_map":{"type":"LINK","mutability":"MUTABLE","data":{"url":"https://en.wikipedia.org/wiki/Riga#cite_note-BilmanisLIS-25","title":"[25]","targetOption":""}}}},"10":{"type":"LINK","mutability":"MUTABLE","data":{"url":"https://en.wikipedia.org/wiki/Riga#cite_note-ACQRxlvi-34","title":"[34]","targetOption":"","_map":{"type":"LINK","mutability":"MUTABLE","data":{"url":"https://en.wikipedia.org/wiki/Riga#cite_note-ACQRxlvi-34","title":"[34]","targetOption":""}}}},"11":{"type":"LINK","mutability":"MUTABLE","data":{"url":"https://en.wikipedia.org/wiki/Riga#cite_note-ACQRxlvi-34","title":"[34]","targetOption":"","_map":{"type":"LINK","mutability":"MUTABLE","data":{"url":"https://en.wikipedia.org/wiki/Riga#cite_note-ACQRxlvi-34","title":"[34]","targetOption":""}}}},"12":{"type":"LINK","mutability":"MUTABLE","data":{"url":"https://en.wikipedia.org/wiki/Riga#cite_note-ACQRxlvi-34","title":"[34]","targetOption":"","_map":{"type":"LINK","mutability":"MUTABLE","data":{"url":"https://en.wikipedia.org/wiki/Riga#cite_note-ACQRxlvi-34","title":"[34]","targetOption":""}}}},"13":{"type":"LINK","mutability":"MUTABLE","data":{"url":"https://en.wikipedia.org/wiki/Riga#cite_note-BilmanisLIS-25","title":"[25]","targetOption":"","_map":{"type":"LINK","mutability":"MUTABLE","data":{"url":"https://en.wikipedia.org/wiki/Riga#cite_note-BilmanisLIS-25","title":"[25]","targetOption":""}}}},"14":{"type":"LINK","mutability":"MUTABLE","data":{"url":"https://en.wikipedia.org/wiki/Riga_Cathedral","title":"Riga Dom","targetOption":"","_map":{"type":"LINK","mutability":"MUTABLE","data":{"url":"https://en.wikipedia.org/wiki/Riga_Cathedral","title":"Riga Dom","targetOption":""}}}},"15":{"type":"LINK","mutability":"MUTABLE","data":{"url":"https://en.wikipedia.org/wiki/Riga#cite_note-35","title":"[35]","targetOption":"","_map":{"type":"LINK","mutability":"MUTABLE","data":{"url":"https://en.wikipedia.org/wiki/Riga#cite_note-35","title":"[35]","targetOption":""}}}},"16":{"type":"LINK","mutability":"MUTABLE","data":{"url":"https://en.wikipedia.org/wiki/Riga#cite_note-ACQRxlvi-34","title":"[34]","targetOption":"","_map":{"type":"LINK","mutability":"MUTABLE","data":{"url":"https://en.wikipedia.org/wiki/Riga#cite_note-ACQRxlvi-34","title":"[34]","targetOption":""}}}},"17":{"type":"LINK","mutability":"MUTABLE","data":{"url":"https://en.wikipedia.org/wiki/Polotsk","title":"Polotsk","targetOption":"","_map":{"type":"LINK","mutability":"MUTABLE","data":{"url":"https://en.wikipedia.org/wiki/Polotsk","title":"Polotsk","targetOption":""}}}},"18":{"type":"LINK","mutability":"MUTABLE","data":{"url":"https://en.wikipedia.org/wiki/Riga#cite_note-PDIntBus-30","title":"[30]","targetOption":"","_map":{"type":"LINK","mutability":"MUTABLE","data":{"url":"https://en.wikipedia.org/wiki/Riga#cite_note-PDIntBus-30","title":"[30]","targetOption":""}}}},"19":{"type":"LINK","mutability":"MUTABLE","data":{"url":"https://en.wikipedia.org/wiki/Koknese","title":"Koknese","targetOption":"","_map":{"type":"LINK","mutability":"MUTABLE","data":{"url":"https://en.wikipedia.org/wiki/Koknese","title":"Koknese","targetOption":""}}}},"20":{"type":"LINK","mutability":"MUTABLE","data":{"url":"https://en.wikipedia.org/wiki/Principality_of_Jersika","title":"Jersika","targetOption":"","_map":{"type":"LINK","mutability":"MUTABLE","data":{"url":"https://en.wikipedia.org/wiki/Principality_of_Jersika","title":"Jersika","targetOption":""}}}},"21":{"type":"LINK","mutability":"MUTABLE","data":{"url":"https://en.wikipedia.org/wiki/Riga#cite_note-MedChronV-36","title":"[36]","targetOption":"","_map":{"type":"LINK","mutability":"MUTABLE","data":{"url":"https://en.wikipedia.org/wiki/Riga#cite_note-MedChronV-36","title":"[36]","targetOption":""}}}}}}}],"id":88940619112,"roles":["knight 292422432828","noble 292422432828","king 292422432828"],"secrets":[{"roles":["knight 292422432828","noble 292422432828","king 292422432828"],"name":"","main":{"blocks":[{"key":"3u6cq","text":"","type":"unstyled","depth":0,"inlineStyleRanges":[],"entityRanges":[],"data":{}}],"entityMap":{}},"sidebar":{"blocks":[{"key":"6dops","text":"","type":"unstyled","depth":0,"inlineStyleRanges":[],"entityRanges":[],"data":{}}],"entityMap":{}}}]}]},{"id":633879941508,"articles":[]}]